liana_mcp/__init__.py
liana_mcp/cli.py
liana_mcp/schema/preset/__int__.py
liana_mcp/schema/preset/ccc.py
liana_mcp/schema/preset/pl.py
liana_mcp/server/__init__.py
liana_mcp/server/preset/ccc.py
liana_mcp/server/preset/pl.py
liana_mcp-0.4.0.dist-info/METADATA
liana_mcp-0.4.0.dist-info/WHEEL
liana_mcp-0.4.0.dist-info/entry_points.txt
liana_mcp-0.4.0.dist-info/RECORD
