Metadata-Version: 2.4
Name: liana-mcp
Version: 0.4.0
Summary: Natural language interface for cell-cell communication analysis with Liana through MCP.
Project-URL: Homepage, http://scmcphub.org/
Project-URL: Repository, https://github.com/scmcphub/liana-mcp
Project-URL: Documentation, https://docs.scmcphub.org/
Author-email: shuang <hsh-me@outlook.com>
Keywords: AI,agent,bioinformatics,llm,mcp,model context protocol,scRNA-seq,single cell
Requires-Python: >=3.10
Requires-Dist: agno
Requires-Dist: fastmcp>=2.3.4
Requires-Dist: liana>=0.1.9
Requires-Dist: mcp>=1.8.0
Requires-Dist: nest-asyncio
Requires-Dist: scanpy
Requires-Dist: scmcp-shared>=0.5.0
